pupil_labs_uvc-1.0.0.dist-info/RECORD
pupil_labs_uvc-1.0.0.dist-info/LICENSE
pupil_labs_uvc-1.0.0.dist-info/WHEEL
pupil_labs_uvc-1.0.0.dist-info/top_level.txt
pupil_labs_uvc-1.0.0.dist-info/METADATA
uvc/uvc_bindings.cpython-311-darwin.so
uvc/__init__.py
uvc/include/libuvc/libuvc.h
uvc/.dylibs/libusb-1.0.0.dylib
uvc/.dylibs/libturbojpeg.0.3.0.dylib
uvc/lib/libuvc.dylib
uvc/lib/libuvc.0.1.0.dylib
uvc/lib/cmake/libuvc/libuvcTargets.cmake
uvc/lib/cmake/libuvc/libuvcTargets-release.cmake
uvc/lib/cmake/libuvc/libuvcConfig.cmake
uvc/lib/cmake/libuvc/libuvcConfigVersion.cmake
