Metadata-Version: 2.1
Name: pupil-labs-uvc
Version: 1.0.0
Summary: Usb Video Class Device bindings with format conversion tool
Home-page: https://github.com/pupil-labs/pyuvc
Author: Pupil Labs GmbH
Author-email: info@pupil-labs.com
License: MIT
Classifier: Development Status :: 5 - Production/Stable
Classifier: Intended Audience :: Developers
Classifier: License :: OSI Approved :: MIT License
Classifier: Programming Language :: Python :: 3
Classifier: Programming Language :: Python :: 3 :: Only
Requires-Python: >=3.6
License-File: LICENSE
Requires-Dist: numpy
Requires-Dist: importlib-metadata ; python_version < "3.8"
Provides-Extra: docs
Requires-Dist: furo ; extra == 'docs'
Requires-Dist: jaraco.packaging >=9 ; extra == 'docs'
Requires-Dist: rst.linker >=1.9 ; extra == 'docs'
Requires-Dist: sphinx ; extra == 'docs'
Provides-Extra: example
Requires-Dist: opencv-python ; extra == 'example'
Requires-Dist: rich ; extra == 'example'
Provides-Extra: testing
Requires-Dist: pytest >=6 ; extra == 'testing'
Requires-Dist: pytest-checkdocs >=2.4 ; extra == 'testing'
Requires-Dist: pytest-cov ; extra == 'testing'
Requires-Dist: pytest-enabler >=1.3 ; extra == 'testing'
Requires-Dist: pytest-mypy >=0.9.1 ; (platform_python_implementation != "PyPy") and extra == 'testing'
